bj/__init__.py
bj-0.0.6.dist-info/licenses/LICENSE
bj-0.0.6.dist-info/METADATA
bj-0.0.6.dist-info/WHEEL
bj-0.0.6.dist-info/top_level.txt
bj-0.0.6.dist-info/RECORD
