Metadata-Version: 2.4
Name: bj
Version: 0.0.6
Summary: Generating hierarchical data
Home-page: https://github.com/t-c-w/bj
Author: Thor Whalen
License: apache-2.0
Platform: any
License-File: LICENSE
Dynamic: license-file
